interactions/ext/wait_for/__init__.py
interactions/ext/wait_for/base.py
interactions/ext/wait_for/classes.py
interactions/ext/wait_for/wait_for.py
interactions_wait_for-1.0.6.dist-info/LICENSE
interactions_wait_for-1.0.6.dist-info/METADATA
interactions_wait_for-1.0.6.dist-info/WHEEL
interactions_wait_for-1.0.6.dist-info/top_level.txt
interactions_wait_for-1.0.6.dist-info/RECORD
