Metadata-Version: 2.1
Name: interactions-wait-for
Version: 1.0.6
Summary: Add a wait_for function to discord-py-interactions
Home-page: https://github.com/Catalyst4222/interactions-wait-for
Author: Catalyst4
Author-email: catalyst4222@gmail.com
License: MIT
Classifier: Programming Language :: Python :: 3
Classifier: Development Status :: 4 - Beta
Classifier: License :: OSI Approved :: MIT License
Classifier: Operating System :: OS Independent
License-File: LICENSE
